{
  "code": 200,
  "msg": "",
  "data": {
    "index":{
      "lt":{
        "b4":{
          "name": "提讯会见",
          "list": [
            {
              "name": "提讯",
              "msg": "21",
              "list":{
                "data":[
                  {"xl":1,"item1":"卢本伟","item2":"男","item3":"健康","item4":"已逮捕","item5":"102","item6":"有"},{"xl":2,"item1":"卢本伟","item2":"男","item3":"健康","item4":"已逮捕","item5":"102","item6":"有"},{"xl":3,"item1":"卢本伟","item2":"男","item3":"健康","item4":"已逮捕","item5":"102","item6":"有"},{"xl":4,"item1":"卢本伟","item2":"男","item3":"健康","item4":"已逮捕","item5":"102","item6":"有"},{"xl":5,"item1":"卢本伟","item2":"男","item3":"健康","item4":"已逮捕","item5":"102","item6":"有"},{"xl":6,"item1":"卢本伟","item2":"男","item3":"健康","item4":"已逮捕","item5":"102","item6":"有"},{"xl":7,"item1":"卢本伟","item2":"男","item3":"健康","item4":"已逮捕","item5":"102","item6":"有"},{"xl":8,"item1":"卢本伟","item2":"男","item3":"健康","item4":"已逮捕","item5":"102","item6":"有"},{"xl":9,"item1":"卢本伟","item2":"男","item3":"健康","item4":"已逮捕","item5":"102","item6":"有"},{"xl":10,"item1":"卢本伟","item2":"男","item3":"健康","item4":"已逮捕","item5":"102","item6":"有"},{"xl":11,"item1":"卢本伟","item2":"男","item3":"健康","item4":"已逮捕","item5":"102","item6":"有"},{"xl":12,"item1":"卢本伟","item2":"男","item3":"健康","item4":"已逮捕","item5":"102","item6":"有"},{"xl":13,"item1":"卢本伟","item2":"男","item3":"健康","item4":"已逮捕","item5":"102","item6":"有"},{"xl":14,"item1":"卢本伟","item2":"男","item3":"健康","item4":"已逮捕","item5":"102","item6":"有"},{"xl":15,"item1":"卢本伟","item2":"男","item3":"健康","item4":"已逮捕","item5":"102","item6":"有"},{"xl":16,"item1":"卢本伟","item2":"男","item3":"健康","item4":"已逮捕","item5":"102","item6":"有"},{"xl":17,"item1":"卢本伟","item2":"男","item3":"健康","item4":"已逮捕","item5":"102","item6":"有"},{"xl":18,"item1":"卢本伟","item2":"男","item3":"健康","item4":"已逮捕","item5":"102","item6":"有"},{"xl":19,"item1":"卢本伟","item2":"男","item3":"健康","item4":"已逮捕","item5":"102","item6":"有"},{"xl":20,"item1":"卢本伟","item2":"男","item3":"健康","item4":"已逮捕","item5":"102","item6":"有"},{"xl":21,"item1":"卢本伟","item2":"男","item3":"健康","item4":"已逮捕","item5":"102","item6":"有"},{"xl":22,"item1":"卢本伟","item2":"男","item3":"健康","item4":"已逮捕","item5":"102","item6":"有"},{"xl":23,"item1":"卢本伟","item2":"男","item3":"健康","item4":"已逮捕","item5":"102","item6":"有"},{"xl":24,"item1":"卢本伟","item2":"男","item3":"健康","item4":"已逮捕","item5":"102","item6":"有"},{"xl":25,"item1":"卢本伟","item2":"男","item3":"健康","item4":"已逮捕","item5":"102","item6":"有"},{"xl":26,"item1":"卢本伟","item2":"男","item3":"健康","item4":"已逮捕","item5":"102","item6":"有"},{"xl":27,"item1":"卢本伟","item2":"男","item3":"健康","item4":"已逮捕","item5":"102","item6":"有"},{"xl":28,"item1":"卢本伟","item2":"男","item3":"健康","item4":"已逮捕","item5":"102","item6":"有"},{"xl":29,"item1":"卢本伟","item2":"男","item3":"健康","item4":"已逮捕","item5":"102","item6":"有"},{"xl":30,"item1":"卢本伟","item2":"男","item3":"健康","item4":"已逮捕","item5":"102","item6":"有"},{"xl":31,"item1":"卢本伟","item2":"男","item3":"健康","item4":"已逮捕","item5":"102","item6":"有"},{"xl":32,"item1":"卢本伟","item2":"男","item3":"健康","item4":"已逮捕","item5":"102","item6":"有"},{"xl":33,"item1":"卢本伟","item2":"男","item3":"健康","item4":"已逮捕","item5":"102","item6":"有"},{"xl":34,"item1":"卢本伟","item2":"男","item3":"健康","item4":"已逮捕","item5":"102","item6":"有"},{"xl":35,"item1":"卢本伟","item2":"男","item3":"健康","item4":"已逮捕","item5":"102","item6":"有"},{"xl":36,"item1":"卢本伟","item2":"男","item3":"健康","item4":"已逮捕","item5":"102","item6":"有"},{"xl":37,"item1":"卢本伟","item2":"男","item3":"健康","item4":"已逮捕","item5":"102","item6":"有"},{"xl":38,"item1":"卢本伟","item2":"男","item3":"健康","item4":"已逮捕","item5":"102","item6":"有"},{"xl":39,"item1":"卢本伟","item2":"男","item3":"健康","item4":"已逮捕","item5":"102","item6":"有"},{"xl":40,"item1":"卢本伟","item2":"男","item3":"健康","item4":"已逮捕","item5":"102","item6":"有"},{"xl":41,"item1":"卢本伟","item2":"男","item3":"健康","item4":"已逮捕","item5":"102","item6":"有"},{"xl":42,"item1":"卢本伟","item2":"男","item3":"健康","item4":"已逮捕","item5":"102","item6":"有"},{"xl":43,"item1":"卢本伟","item2":"男","item3":"健康","item4":"已逮捕","item5":"102","item6":"有"},{"xl":44,"item1":"卢本伟","item2":"男","item3":"健康","item4":"已逮捕","item5":"102","item6":"有"},{"xl":45,"item1":"卢本伟","item2":"男","item3":"健康","item4":"已逮捕","item5":"102","item6":"有"},{"xl":46,"item1":"卢本伟","item2":"男","item3":"健康","item4":"已逮捕","item5":"102","item6":"有"},{"xl":47,"item1":"卢本伟","item2":"男","item3":"健康","item4":"已逮捕","item5":"102","item6":"有"},{"xl":48,"item1":"卢本伟","item2":"男","item3":"健康","item4":"已逮捕","item5":"102","item6":"有"},{"xl":49,"item1":"卢本伟","item2":"男","item3":"健康","item4":"已逮捕","item5":"102","item6":"有"},{"xl":50,"item1":"卢本伟","item2":"男","item3":"健康","item4":"已逮捕","item5":"102","item6":"有"},{"xl":51,"item1":"卢本伟","item2":"男","item3":"健康","item4":"已逮捕","item5":"102","item6":"有"},{"xl":52,"item1":"卢本伟","item2":"男","item3":"健康","item4":"已逮捕","item5":"102","item6":"有"},{"xl":53,"item1":"卢本伟","item2":"男","item3":"健康","item4":"已逮捕","item5":"102","item6":"有"},{"xl":54,"item1":"卢本伟","item2":"男","item3":"健康","item4":"已逮捕","item5":"102","item6":"有"},{"xl":55,"item1":"卢本伟","item2":"男","item3":"健康","item4":"已逮捕","item5":"102","item6":"有"},{"xl":56,"item1":"卢本伟","item2":"男","item3":"健康","item4":"已逮捕","item5":"102","item6":"有"},{"xl":57,"item1":"卢本伟","item2":"男","item3":"健康","item4":"已逮捕","item5":"102","item6":"有"},{"xl":58,"item1":"卢本伟","item2":"男","item3":"健康","item4":"已逮捕","item5":"102","item6":"有"},{"xl":59,"item1":"卢本伟","item2":"男","item3":"健康","item4":"已逮捕","item5":"102","item6":"有"},{"xl":60,"item1":"卢本伟","item2":"男","item3":"健康","item4":"已逮捕","item5":"102","item6":"有"},{"xl":61,"item1":"卢本伟","item2":"男","item3":"健康","item4":"已逮捕","item5":"102","item6":"有"},{"xl":62,"item1":"卢本伟","item2":"男","item3":"健康","item4":"已逮捕","item5":"102","item6":"有"},{"xl":63,"item1":"卢本伟","item2":"男","item3":"健康","item4":"已逮捕","item5":"102","item6":"有"},{"xl":64,"item1":"卢本伟","item2":"男","item3":"健康","item4":"已逮捕","item5":"102","item6":"有"},{"xl":65,"item1":"卢本伟","item2":"男","item3":"健康","item4":"已逮捕","item5":"102","item6":"有"},{"xl":66,"item1":"卢本伟","item2":"男","item3":"健康","item4":"已逮捕","item5":"102","item6":"有"},{"xl":67,"item1":"卢本伟","item2":"男","item3":"健康","item4":"已逮捕","item5":"102","item6":"有"},{"xl":68,"item1":"卢本伟","item2":"男","item3":"健康","item4":"已逮捕","item5":"102","item6":"有"},{"xl":69,"item1":"卢本伟","item2":"男","item3":"健康","item4":"已逮捕","item5":"102","item6":"有"},{"xl":70,"item1":"卢本伟","item2":"男","item3":"健康","item4":"已逮捕","item5":"102","item6":"有"},{"xl":71,"item1":"卢本伟","item2":"男","item3":"健康","item4":"已逮捕","item5":"102","item6":"有"},{"xl":72,"item1":"卢本伟","item2":"男","item3":"健康","item4":"已逮捕","item5":"102","item6":"有"},{"xl":73,"item1":"卢本伟","item2":"男","item3":"健康","item4":"已逮捕","item5":"102","item6":"有"},{"xl":74,"item1":"卢本伟","item2":"男","item3":"健康","item4":"已逮捕","item5":"102","item6":"有"},{"xl":75,"item1":"卢本伟","item2":"男","item3":"健康","item4":"已逮捕","item5":"102","item6":"有"},{"xl":76,"item1":"卢本伟","item2":"男","item3":"健康","item4":"已逮捕","item5":"102","item6":"有"},{"xl":77,"item1":"卢本伟","item2":"男","item3":"健康","item4":"已逮捕","item5":"102","item6":"有"},{"xl":78,"item1":"卢本伟","item2":"男","item3":"健康","item4":"已逮捕","item5":"102","item6":"有"},{"xl":79,"item1":"卢本伟","item2":"男","item3":"健康","item4":"已逮捕","item5":"102","item6":"有"},{"xl":80,"item1":"卢本伟","item2":"男","item3":"健康","item4":"已逮捕","item5":"102","item6":"有"},{"xl":81,"item1":"卢本伟","item2":"男","item3":"健康","item4":"已逮捕","item5":"102","item6":"有"},{"xl":82,"item1":"卢本伟","item2":"男","item3":"健康","item4":"已逮捕","item5":"102","item6":"有"},{"xl":83,"item1":"卢本伟","item2":"男","item3":"健康","item4":"已逮捕","item5":"102","item6":"有"},{"xl":84,"item1":"卢本伟","item2":"男","item3":"健康","item4":"已逮捕","item5":"102","item6":"有"},{"xl":85,"item1":"卢本伟","item2":"男","item3":"健康","item4":"已逮捕","item5":"102","item6":"有"},{"xl":86,"item1":"卢本伟","item2":"男","item3":"健康","item4":"已逮捕","item5":"102","item6":"有"},{"xl":87,"item1":"卢本伟","item2":"男","item3":"健康","item4":"已逮捕","item5":"102","item6":"有"},{"xl":88,"item1":"卢本伟","item2":"男","item3":"健康","item4":"已逮捕","item5":"102","item6":"有"},{"xl":89,"item1":"卢本伟","item2":"男","item3":"健康","item4":"已逮捕","item5":"102","item6":"有"},{"xl":90,"item1":"卢本伟","item2":"男","item3":"健康","item4":"已逮捕","item5":"102","item6":"有"},{"xl":91,"item1":"卢本伟","item2":"男","item3":"健康","item4":"已逮捕","item5":"102","item6":"有"},{"xl":92,"item1":"卢本伟","item2":"男","item3":"健康","item4":"已逮捕","item5":"102","item6":"有"},{"xl":93,"item1":"卢本伟","item2":"男","item3":"健康","item4":"已逮捕","item5":"102","item6":"有"},{"xl":94,"item1":"卢本伟","item2":"男","item3":"健康","item4":"已逮捕","item5":"102","item6":"有"},{"xl":95,"item1":"卢本伟","item2":"男","item3":"健康","item4":"已逮捕","item5":"102","item6":"有"},{"xl":96,"item1":"卢本伟","item2":"男","item3":"健康","item4":"已逮捕","item5":"102","item6":"有"},{"xl":97,"item1":"卢本伟","item2":"男","item3":"健康","item4":"已逮捕","item5":"102","item6":"有"},{"xl":98,"item1":"卢本伟","item2":"男","item3":"健康","item4":"已逮捕","item5":"102","item6":"有"},{"xl":99,"item1":"卢本伟","item2":"男","item3":"健康","item4":"已逮捕","item5":"102","item6":"有"},{"xl":100,"item1":"卢本伟","item2":"男","item3":"健康","item4":"已逮捕","item5":"102","item6":"有"}
                ],
                "seriesNum":7,
                "titles":[
                  {"series":"xl","name":"序号"},
                  {"series":"item1","name":"姓名"},
                  {"series":"item2","name":"性别"},
                  {"series":"item3","name":"健康情况"},
                  {"series":"item4","name":"逮捕情况"},
                  {"series":"item5","name":"监室号"},
                  {"series":"item6","name":"有无其他犯罪记录"}
                ]
              }
            },
            {
              "name": "家属会见",
              "msg": "0"
            },
            {
              "name": "律师会见",
              "msg": "18"
            }
          ]
        }
      }      
    }
  }
}